dquadratic/__init__.py
dquadratic/feature1.py
dquadratic/feature2.py
dquadratic-0.1.0.dist-info/licenses/LICENSE
dquadratic-0.1.0.dist-info/METADATA
dquadratic-0.1.0.dist-info/WHEEL
dquadratic-0.1.0.dist-info/top_level.txt
dquadratic-0.1.0.dist-info/RECORD
